agentkit/__init__.py
agentkit/version.py
agentkit/apps/__init__.py
agentkit/apps/base_app.py
agentkit/apps/utils.py
agentkit/apps/a2a_app/__init__.py
agentkit/apps/a2a_app/a2a_app.py
agentkit/apps/a2a_app/telemetry.py
agentkit/apps/agent_server_app/__init__.py
agentkit/apps/agent_server_app/agent_server_app.py
agentkit/apps/mcp_app/__init__.py
agentkit/apps/mcp_app/mcp_app.py
agentkit/apps/mcp_app/telemetry.py
agentkit/apps/simple_app/__init__.py
agentkit/apps/simple_app/simple_app.py
agentkit/apps/simple_app/simple_app_handlers.py
agentkit/apps/simple_app/telemetry.py
agentkit/gateway/__init__.py
agentkit/identity/__init__.py
agentkit/knowledge/__init__.py
agentkit/memory/__init__.py
agentkit/memory/memory.py
agentkit/memory/memory_sdk.py
agentkit/runtime/__init__.py
agentkit/runtime/runtime.py
agentkit/runtime/types.py
agentkit/toolkit/__init__.py
agentkit/toolkit/cli/__init__.py
agentkit/toolkit/cli/__main__.py
agentkit/toolkit/cli/cli.py
agentkit/toolkit/config/__init__.py
agentkit/toolkit/config/auto_prompt.py
agentkit/toolkit/config/config.py
agentkit/toolkit/config/constants.py
agentkit/toolkit/config/dataclass_utils.py
agentkit/toolkit/integrations/__init__.py
agentkit/toolkit/integrations/container.py
agentkit/toolkit/integrations/ve_code_pipeline.py
agentkit/toolkit/integrations/ve_cr.py
agentkit/toolkit/integrations/ve_iam.py
agentkit/toolkit/integrations/builder/__init__.py
agentkit/toolkit/integrations/builder/base.py
agentkit/toolkit/integrations/builder/local_docker_builder.py
agentkit/toolkit/integrations/builder/ve_core_pipeline_builder.py
agentkit/toolkit/integrations/runner/__init__.py
agentkit/toolkit/integrations/runner/base.py
agentkit/toolkit/integrations/runner/local_docker_runner.py
agentkit/toolkit/integrations/runner/ve_agentkit_runner.py
agentkit/toolkit/integrations/services/__init__.py
agentkit/toolkit/integrations/services/code_pipeline_service.py
agentkit/toolkit/integrations/services/cr_service.py
agentkit_sdk_python_inhouse_nightly-0.0.7.5.dist-info/licenses/LICENSE
agentkit_sdk_python_inhouse_nightly-0.0.7.5.dist-info/METADATA
agentkit_sdk_python_inhouse_nightly-0.0.7.5.dist-info/WHEEL
agentkit_sdk_python_inhouse_nightly-0.0.7.5.dist-info/entry_points.txt
agentkit_sdk_python_inhouse_nightly-0.0.7.5.dist-info/top_level.txt
agentkit_sdk_python_inhouse_nightly-0.0.7.5.dist-info/RECORD
