Metadata-Version: 2.4
Name: agentkit-sdk-python-inhouse-nightly
Version: 0.0.7.5
Summary: Python SDK for transforming any AI agent into a production-ready application. Framework-agnostic primitives for runtime, memory, authentication, and tools with volcengine-managed infrastructure.
Author-email: Yaozheng Fang <fangyozheng@gmail.com>, Guodong Li <cu.eric.lee@gmail.com>, Xiangrui Cheng <innsdcc@gmail.com>
License:                                  Apache License
Requires-Python: >=3.10
License-File: LICENSE
Requires-Dist: a2a-sdk>=0.3.7
Requires-Dist: fastapi>=0.117.1
Requires-Dist: fastmcp>=2.12.3
Requires-Dist: opentelemetry-api>=1.32.1
Requires-Dist: opentelemetry-exporter-otlp-proto-common>=1.32.1
Requires-Dist: opentelemetry-exporter-otlp-proto-grpc>=1.32.1
Requires-Dist: opentelemetry-sdk>=1.32.1
Requires-Dist: pydantic>=2.11.9
Requires-Dist: requests>=2.32.5
Requires-Dist: uvicorn>=0.37.0
Requires-Dist: pyyaml
Requires-Dist: prompt_toolkit
Requires-Dist: typing
Requires-Dist: typer
Requires-Dist: rich
Requires-Dist: docker
Requires-Dist: jinja2
Requires-Dist: tos>=2.8.7
Provides-Extra: extensions
Provides-Extra: toolkit
Provides-Extra: dev
Dynamic: license-file
